src/__init__.py
src/commands/add.py
src/commands/init.py
src/commands/install.py
src/commands/list.py
src/commands/version.py
src/main.py
src/modukit_binary.py
src/statics/environments.py
src/utils/binaries.py
src/utils/modules.py
modukit_dj-0.0.13.dist-info/METADATA
modukit_dj-0.0.13.dist-info/WHEEL
modukit_dj-0.0.13.dist-info/entry_points.txt
modukit_dj-0.0.13.dist-info/RECORD
