Metadata-Version: 2.3
Name: modukit-dj
Version: 0.0.13
Summary: A CLI tool for managing ModuKit Django Modules
Author: Nameer Haider
Author-email: nmeer5242@gmail.com
Requires-Python: >=3.12
Classifier: Programming Language :: Python :: 3
Classifier: Programming Language :: Python :: 3.12
Classifier: Programming Language :: Python :: 3.13
Requires-Dist: dotenv (>=0.9.9,<0.10.0)
Requires-Dist: requests (>=2.32.3,<3.0.0)
Requires-Dist: tabulate (>=0.9.0,<0.10.0)
Requires-Dist: typer (>=0.15.3,<0.16.0)
